pdag/__init__.py
pdag/_cli.py
pdag/py.typed
pdag/_core/__init__.py
pdag/_core/collection.py
pdag/_core/model.py
pdag/_core/parameter.py
pdag/_core/reference.py
pdag/_core/relationship.py
pdag/_exec/__init__.py
pdag/_exec/core.py
pdag/_exec/model.py
pdag/_exec/ref_resolver.py
pdag/_exec/to_exec_model.py
pdag/_exec/utils.py
pdag/_experiment/__init__.py
pdag/_experiment/cases.py
pdag/_experiment/distance_sampling.py
pdag/_experiment/multi_process.py
pdag/_experiment/results.py
pdag/_experiment/runner.py
pdag/_export/__init__.py
pdag/_export/dot.py
pdag/_export/html.py
pdag/_export/assets/graph.j2
pdag/_notation/__init__.py
pdag/_notation/decorators.py
pdag/_notation/export.py
pdag/_notation/model.py
pdag/_utils/__init__.py
pdag/_utils/ast_utils.py
pdag/_utils/dict_utils.py
pdag/_utils/init_args_recorder.py
pdag/_utils/multidef.py
pdag/_utils/random_string.py
pdag/_utils/topological_sort.py
pdag/examples/__init__.py
pdag/examples/_diamond_mdp.py
pdag/examples/_each_squared.py
pdag/examples/_polynomials.py
pdag/examples/_square.py
pdag/examples/_squares.py
pdag/examples/_treasure.py
pdag/examples/_umbrella.py
pdag-0.0.15.dist-info/METADATA
pdag-0.0.15.dist-info/WHEEL
pdag-0.0.15.dist-info/entry_points.txt
pdag-0.0.15.dist-info/licenses/LICENSE
pdag-0.0.15.dist-info/RECORD
