Metadata-Version: 2.4
Name: pdag
Version: 0.0.15
Summary: A Python package that helps you create and execute a directed acyclic graph (DAG) of parameters and their relationships.
Project-URL: Documentation, https://shunichironomura.github.io/pdag/
Project-URL: Repository, https://github.com/shunichironomura/pdag
Project-URL: Issues, https://github.com/shunichironomura/pdag/issues
Author-email: Shunichiro Nomura <nomura@space.t.u-tokyo.ac.jp>
License-Expression: MIT
License-File: LICENSE
Classifier: Development Status :: 3 - Alpha
Classifier: Intended Audience :: Science/Research
Classifier: License :: OSI Approved :: MIT License
Classifier: Programming Language :: Python
Classifier: Programming Language :: Python :: 3 :: Only
Classifier: Programming Language :: Python :: 3.12
Classifier: Programming Language :: Python :: 3.13
Classifier: Topic :: Scientific/Engineering
Classifier: Typing :: Typed
Requires-Python: >=3.12
Requires-Dist: asttokens>=3.0.0
Requires-Dist: jinja2>=3.1.6
Requires-Dist: mpire>=2.10.2
Requires-Dist: numpy>=1.24
Requires-Dist: polars>=1.24.0
Requires-Dist: pyarrow>=19.0.1
Requires-Dist: pydantic>=2.11.7
Requires-Dist: pydot>=3.0.4
Requires-Dist: rich>=13.9.4
Requires-Dist: tqdm>=4.67.1
Requires-Dist: typer>=0.15.2
Requires-Dist: typing-extensions>=4.12.2
Requires-Dist: watchfiles>=1.0.4
